videoguys/__init__.py
videoguys/clients/__init__.py
videoguys/clients/api.py
videoguys/clients/download.py
videoguys/clients/upload.py
videoguys-0.0.4.dist-info/LICENSE
videoguys-0.0.4.dist-info/METADATA
videoguys-0.0.4.dist-info/WHEEL
videoguys-0.0.4.dist-info/top_level.txt
videoguys-0.0.4.dist-info/RECORD
