Metadata-Version: 2.1
Name: videoguys
Version: 0.0.4
Summary: Video API
Home-page: https://github.com/VideoGuys/python-client
Author-email: 
License: UNKNOWN
Keywords: Video API,Video Guys,Vevio,Vidup
Platform: UNKNOWN
Requires-Dist: simple-rest-client (==0.5.4)
